IPv4Rechner/IPv4.py
IPv4Rechner/__init__.py
IPv4Rechner-1.1.dist-info/LICENSE
IPv4Rechner-1.1.dist-info/METADATA
IPv4Rechner-1.1.dist-info/WHEEL
IPv4Rechner-1.1.dist-info/top_level.txt
IPv4Rechner-1.1.dist-info/RECORD
