Metadata-Version: 2.1
Name: IPv4Rechner
Version: 1.1
Summary: Paket zum Berechnen von IPv4 Adressen.
Home-page: https://github.com/comiker91
Author: comiker91
Author-email: webmaster@nightmaremc.de
License: UNKNOWN
Platform: UNKNOWN
Classifier: Programming Language :: Python :: 3
Classifier: License :: OSI Approved :: MIT License
Classifier: Operating System :: OS Independent
Requires-Python: >=3.6
